httpcgi/__init__.py
httpcgi/http_cgi.py
libcgipy-0.1.2.2.dist-info/METADATA
libcgipy-0.1.2.2.dist-info/WHEEL
libcgipy-0.1.2.2.dist-info/top_level.txt
libcgipy-0.1.2.2.dist-info/RECORD
